interrogate/__init__.py
interrogate/__main__.py
interrogate/interrogate.exe
interrogate_module/__init__.py
interrogate_module/__main__.py
interrogate_module/interrogate_module.exe
interrogatedb.cp313t-win_amd64.pyd
interrogatedb.pyi
panda3d_interrogate-0.9.0.dist-info/METADATA
panda3d_interrogate-0.9.0.dist-info/WHEEL
panda3d_interrogate-0.9.0.dist-info/entry_points.txt
panda3d_interrogate-0.9.0.dist-info/licenses/LICENSE
panda3d_interrogate-0.9.0.dist-info/RECORD
