Metadata-Version: 2.2
Name: panda3d-interrogate
Version: 0.9.0
Summary: Binding generator designed for Panda3D
License: Copyright (c) 2008, Carnegie Mellon University.
Classifier: Development Status :: 5 - Production/Stable
Classifier: Intended Audience :: Developers
Classifier: License :: OSI Approved :: BSD License
Classifier: Operating System :: OS Independent
Classifier: Programming Language :: C++
Project-URL: Source, https://github.com/panda3d/interrogate
Project-URL: Tracker, https://github.com/panda3d/interrogate/issues
Project-URL: Funding, https://opencollective.com/panda3d
Requires-Python: >=3.2
